git_remote_s3/__init__.py
git_remote_s3/common.py
git_remote_s3/enums.py
git_remote_s3/git.py
git_remote_s3/lfs.py
git_remote_s3/manage.py
git_remote_s3/remote.py
git_remote_s3-0.3.0.dist-info/METADATA
git_remote_s3-0.3.0.dist-info/WHEEL
git_remote_s3-0.3.0.dist-info/entry_points.txt
git_remote_s3-0.3.0.dist-info/licenses/LICENSE
git_remote_s3-0.3.0.dist-info/licenses/NOTICE
git_remote_s3-0.3.0.dist-info/RECORD
